LICENSE
README.md
setup.cfg
setup.py
DMCGridFinder.egg-info/PKG-INFO
DMCGridFinder.egg-info/SOURCES.txt
DMCGridFinder.egg-info/dependency_links.txt
DMCGridFinder.egg-info/requires.txt
DMCGridFinder.egg-info/top_level.txt
gridfinder/__init__.py
gridfinder/error_function.py
gridfinder/metrics.py
gridfinder/pattern_creator.py
gridfinder/rotation.py
gridfinder/translation.py
gridfinder/utils.py
gridfinder/guided/GAT.py
gridfinder/guided/GC.py
gridfinder/guided/__init__.py
gridfinder/unguided/CDCR.py
gridfinder/unguided/UGAT.py
gridfinder/unguided/UGC.py
gridfinder/unguided/__init__.py
test/__init__.py
test/test_CDCR.py
test/test_guided.py
test/test_metrics.py
test/test_pattern_creator.py
test/test_rotation.py
test/test_translation.py
test/test_unguided.py