Metadata-Version: 2.1
Name: DMCGridFinder
Version: 0.0.1
Summary: Approximate DMC target positions from sets of coordinates
Home-page: 
Author: P. Bischoff
Author-email: peter.bischoff@ikts.fraunhofer.de
Classifier: Programming Language :: Python :: 3
Requires-Python: >=3.9
License-File: LICENSE
